ECOv002_CMR/ECOSTRESS_CMR_search.py
ECOv002_CMR/ECOSTRESS_CMR_search_links.py
ECOv002_CMR/ECOv002_CMR.py
ECOv002_CMR/__init__.py
ECOv002_CMR/concept_ID_from_DOI.py
ECOv002_CMR/constants.py
ECOv002_CMR/download_ECOSTRESS_granule.py
ECOv002_CMR/download_ECOSTRESS_granule_files.py
ECOv002_CMR/download_file.py
ECOv002_CMR/exceptions.py
ECOv002_CMR/granule_ID.py
ECOv002_CMR/granule_ID_from_filename.py
ECOv002_CMR/interpret_ECOSTRESS_URLs.py
ECOv002_CMR/product_name_from_filename.py
ECOv002_CMR/variable_from_filename.py
ECOv002_CMR/version.txt
ECOv002_CMR/timer/__init__.py
ECOv002_CMR/timer/timer.py
ecov002_cmr-1.1.0.dist-info/licenses/LICENSE
ecov002_cmr-1.1.0.dist-info/METADATA
ecov002_cmr-1.1.0.dist-info/WHEEL
ecov002_cmr-1.1.0.dist-info/top_level.txt
ecov002_cmr-1.1.0.dist-info/RECORD
