Metadata-Version: 2.4
Name: ECOv002_CMR
Version: 1.1.0
Summary: Common Metadata Repository (CMR) Search for ECOSTRESS Collection 2
Author-email: "Gregory H. Halverson" <gregory.h.halverson@jpl.nasa.gov>
Project-URL: Homepage, https://github.com/ECOSTRESS-Collection-2/ECOv002-CMR
Classifier: Programming Language :: Python :: 3
Classifier: Operating System :: OS Independent
Requires-Python: >=3.10
License-File: LICENSE
Requires-Dist: colored-logging
Requires-Dist: ECOv002-granules
Requires-Dist: numpy
Requires-Dist: pandas
Requires-Dist: rasters>=1.3.6
Requires-Dist: requests
Requires-Dist: sentinel-tiles
Requires-Dist: tqdm
Provides-Extra: dev
Requires-Dist: build; extra == "dev"
Requires-Dist: pytest>=6.0; extra == "dev"
Requires-Dist: pytest-cov; extra == "dev"
Requires-Dist: jupyter; extra == "dev"
Requires-Dist: pytest; extra == "dev"
Requires-Dist: twine; extra == "dev"
Dynamic: license-file
